cmd_aliases/__init__.py
cmd_aliases/aliased_group.py
cmd_aliases/config.py
cli_aliases-0.0.1.dist-info/LICENSE
cli_aliases-0.0.1.dist-info/METADATA
cli_aliases-0.0.1.dist-info/WHEEL
cli_aliases-0.0.1.dist-info/top_level.txt
cli_aliases-0.0.1.dist-info/RECORD
