Metadata-Version: 2.2
Name: cli-aliases
Version: 0.0.1
Summary: `cli-aliases` implements command line aliases using the Click package.
Author-email: Jeff Wang <jkwang@usc.edu>
License: MIT License
Project-URL: Source, https://github.com/jeffkwang/cli-aliases
Project-URL: Tip Me, https://buymeacoffee.com/jeffkwang
Keywords: cli,Click
Classifier: Programming Language :: Python :: 3.13
Classifier: Development Status :: 3 - Alpha
Classifier: Intended Audience :: Developers
Classifier:  Topic :: Software Development :: Libraries :: Python Modules
Classifier: License :: OSI Approved :: MIT License
Requires-Python: >=3.12
License-File: LICENSE
Requires-Dist: Click
